{
  "source": "Suno Library",
  "account": "neocyber1",
  "page": 365,
  "count": 14,
  "capturedAt": "2026-07-13T03:48:43.180Z",
  "tracks": [
    {
      "artwork": "https://cdn2.suno.ai/image_e97fae07-67c4-4aad-9570-08168ed5845a.jpeg?width=100",
      "duration": "2:23",
      "id": "e97fae07-67c4-4aad-9570-08168ed5845a",
      "rawText": "2:23Oh Honey, Don’t Dov5mexictrapDidi1PublishRemix",
      "title": "Oh Honey, Don’t Do",
      "url": "https://suno.com/song/e97fae07-67c4-4aad-9570-08168ed5845a",
      "version": "v5",
      "page": 365
    },
    {
      "artwork": "https://cdn2.suno.ai/image_d9adcf8c-b02a-42cd-997e-4c658eff17ca.jpeg?width=100",
      "duration": "2:13",
      "id": "d9adcf8c-b02a-42cd-997e-4c658eff17ca",
      "rawText": "2:13Oh Honey, Don’t Dov5mexictrapDidi1PublishRemix",
      "title": "Oh Honey, Don’t Do",
      "url": "https://suno.com/song/d9adcf8c-b02a-42cd-997e-4c658eff17ca",
      "version": "v5",
      "page": 365
    },
    {
      "artwork": "https://cdn2.suno.ai/image_6f267539-21fc-4138-ae6f-affbb8f38ca8.jpeg?width=100",
      "duration": "7:59",
      "id": "6f267539-21fc-4138-ae6f-affbb8f38ca8",
      "rawText": "7:59Oh Honey, Don’t Dov5mexictrap1PublishRemix",
      "title": "Oh Honey, Don’t Do",
      "url": "https://suno.com/song/6f267539-21fc-4138-ae6f-affbb8f38ca8",
      "version": "v5",
      "page": 365
    },
    {
      "artwork": "https://cdn2.suno.ai/image_b42feb57-0ebc-4276-8a71-d869239a3f7f.jpeg?width=100",
      "duration": "1:54",
      "id": "b42feb57-0ebc-4276-8a71-d869239a3f7f",
      "rawText": "1:54Oh Honey, Don’t Dov5mexictrap1PublishRemix",
      "title": "Oh Honey, Don’t Do",
      "url": "https://suno.com/song/b42feb57-0ebc-4276-8a71-d869239a3f7f",
      "version": "v5",
      "page": 365
    },
    {
      "artwork": "https://cdn2.suno.ai/image_2ed8bc3b-e7fe-472c-8e3c-50cd4ec80589.jpeg?width=100",
      "duration": "1:18",
      "id": "2ed8bc3b-e7fe-472c-8e3c-50cd4ec80589",
      "rawText": "1:18Oh Honey, Don’t Dov5mexictrapDidi1PublishRemix",
      "title": "Oh Honey, Don’t Do",
      "url": "https://suno.com/song/2ed8bc3b-e7fe-472c-8e3c-50cd4ec80589",
      "version": "v5",
      "page": 365
    },
    {
      "artwork": "https://cdn2.suno.ai/image_e1840416-c49f-4a25-aedc-056fc412939f.jpeg?width=100",
      "duration": "7:13",
      "id": "e1840416-c49f-4a25-aedc-056fc412939f",
      "rawText": "7:13Oh Honey, Don’t Dov5mexictrapDidi2PublishRemix",
      "title": "Oh Honey, Don’t Do",
      "url": "https://suno.com/song/e1840416-c49f-4a25-aedc-056fc412939f",
      "version": "v5",
      "page": 365
    },
    {
      "artwork": "https://cdn2.suno.ai/image_7cad051e-81b4-4d1a-989b-4dedbe697640.jpeg?width=100",
      "duration": "2:18",
      "id": "7cad051e-81b4-4d1a-989b-4dedbe697640",
      "rawText": "2:18Oh Honey, Don’t Dov5mexictrapDidi1PublishRemix",
      "title": "Oh Honey, Don’t Do",
      "url": "https://suno.com/song/7cad051e-81b4-4d1a-989b-4dedbe697640",
      "version": "v5",
      "page": 365
    },
    {
      "artwork": "https://cdn2.suno.ai/image_603fe484-7575-4eae-9d47-e994f1374fe0.jpeg?width=100",
      "duration": "2:36",
      "id": "603fe484-7575-4eae-9d47-e994f1374fe0",
      "rawText": "2:36Oh Honey, Don’t Dov5mexictrapDidi3PublishRemix",
      "title": "Oh Honey, Don’t Do",
      "url": "https://suno.com/song/603fe484-7575-4eae-9d47-e994f1374fe0",
      "version": "v5",
      "page": 365
    },
    {
      "artwork": "https://cdn2.suno.ai/image_686d9a22-afe8-4cfb-8bc9-9a71ac60275d.jpeg?width=100",
      "duration": "2:41",
      "id": "686d9a22-afe8-4cfb-8bc9-9a71ac60275d",
      "rawText": "2:41Oh Honey, Don’t Dov5Mexictrap2PublishRemix",
      "title": "Oh Honey, Don’t Do",
      "url": "https://suno.com/song/686d9a22-afe8-4cfb-8bc9-9a71ac60275d",
      "version": "v5",
      "page": 365
    },
    {
      "artwork": "https://cdn2.suno.ai/image_09c5ac29-f641-499e-a0b1-a2ad0e04b613.jpeg?width=100",
      "duration": "2:50",
      "id": "09c5ac29-f641-499e-a0b1-a2ad0e04b613",
      "rawText": "2:50Oh Honey, Don’t Dov5Mexictrap1PublishRemix",
      "title": "Oh Honey, Don’t Do",
      "url": "https://suno.com/song/09c5ac29-f641-499e-a0b1-a2ad0e04b613",
      "version": "v5",
      "page": 365
    },
    {
      "artwork": "https://cdn2.suno.ai/image_1104d43e-43f3-46fa-9e0e-a2c3b75b96ff.jpeg?width=100",
      "duration": "7:59",
      "id": "1104d43e-43f3-46fa-9e0e-a2c3b75b96ff",
      "rawText": "7:59Traigo en el pecho un mapa de luz,v5Metal + Reggae + Dub Technometreggaedub2PublishRemix",
      "title": "Traigo en el pecho un mapa de luz,",
      "url": "https://suno.com/song/1104d43e-43f3-46fa-9e0e-a2c3b75b96ff",
      "version": "v5",
      "page": 365
    },
    {
      "artwork": "https://cdn2.suno.ai/image_02257de8-fd69-4af4-8649-236e24eba6c2.jpeg?width=100",
      "duration": "2:56",
      "id": "02257de8-fd69-4af4-8649-236e24eba6c2",
      "rawText": "2:56Traigo en el pecho un mapa de luz,v5Metal + Reggae + Dub Technometreggaedub21PublishRemix",
      "title": "Traigo en el pecho un mapa de luz,",
      "url": "https://suno.com/song/02257de8-fd69-4af4-8649-236e24eba6c2",
      "version": "v5",
      "page": 365
    },
    {
      "artwork": "https://cdn2.suno.ai/image_e05b80e0-75b8-4e00-9824-8e77be3a76e2.jpeg?width=100",
      "duration": "3:07",
      "id": "e05b80e0-75b8-4e00-9824-8e77be3a76e2",
      "rawText": "3:07Traigo en el pecho un mapa de luz,v5Metal + Reggae + Dub Technometreggaedub1PublishRemix",
      "title": "Traigo en el pecho un mapa de luz,",
      "url": "https://suno.com/song/e05b80e0-75b8-4e00-9824-8e77be3a76e2",
      "version": "v5",
      "page": 365
    },
    {
      "artwork": "https://cdn2.suno.ai/image_fce30390-f4b0-458c-8945-3138720af2b2.jpeg?width=100",
      "duration": "4:17",
      "id": "fce30390-f4b0-458c-8945-3138720af2b2",
      "rawText": "4:17Traigo en el pecho un mapa de luz,v5Metal + Reggae + Dub TechnometreggaedubPublishRemix",
      "title": "Traigo en el pecho un mapa de luz,",
      "url": "https://suno.com/song/fce30390-f4b0-458c-8945-3138720af2b2",
      "version": "v5",
      "page": 365
    }
  ]
}